[
  {
    "brand": "IWC",
    "articul": "IW328201",
    "source_url": "https://www.caratco.com/products/iw328201",
    "source_tier": "reputable",
    "confidence_status": "partial",
    "error": "",
    "name": "IWC Пилотские часы Марк XX IW328201",
    "collection": "Пилотские часы",
    "mechanism": "Механический",
    "caliber": "32111",
    "diameter": "40 мм",
    "water_resistance": "100 м"
  },
  {
    "brand": "Piaget",
    "articul": "G0A45005",
    "source_url": "https://www.watches-of-switzerland.co.uk/Piaget-Polo-G0A45005/p/17800567",
    "source_tier": "reputable",
    "confidence_status": "partial",
    "error": "",
    "name": "Piaget Polo G0A45005",
    "collection": "Polo",
    "mechanism": "Механический",
    "caliber": "1110P",
    "diameter": "42 мм",
    "water_resistance": "100 м"
  },
  {
    "brand": "Swatch",
    "articul": "SO33M100",
    "source_url": "https://www.swatch.com/en-my/mission-to-the-moon-so33m100/SO33M100.html",
    "source_tier": "unknown",
    "confidence_status": "partial",
    "error": "",
    "name": "Swatch Bioceramic MoonSwatch SO33M100",
    "collection": "Bioceramic MoonSwatch",
    "mechanism": "Кварцевый",
    "caliber": "ETA G10.212 AB ND",
    "diameter": "42 мм",
    "water_resistance": "30 м"
  },
  {
    "brand": "U-BOAT",
    "articul": "8464",
    "source_url": "https://www.gnomonwatches.com/products/darkmoon-44mm-ipb-ref-8464-b",
    "source_tier": "unknown",
    "confidence_status": "partial",
    "error": "",
    "name": "U-Boat Darkmoon 8464/B",
    "collection": "Darkmoon",
    "mechanism": "Кварцевый",
    "caliber": "Ronda 712.3",
    "diameter": "44 мм",
    "water_resistance": "50 м"
  },
  {
    "brand": "Audemars Piguet",
    "articul": "15510ST.OO.1320ST.06",
    "source_url": "https://www.audemarspiguet.com/com/en/watch-collection/royal-oak/15510ST.OO.1320ST.06.html",
    "source_tier": "official",
    "confidence_status": "partial",
    "error": "",
    "name": "Audemars Piguet Royal Oak Selfwinding 15510ST.OO.1320ST.06",
    "collection": "Royal Oak",
    "mechanism": "Механический",
    "caliber": "4302",
    "diameter": "41 мм",
    "water_resistance": "50 м"
  },
  {
    "brand": "Bvlgari",
    "articul": "103481",
    "source_url": "https://www.thewatchpages.com/watches/bulgari-octo-roma-worldtimer-steel-103481/",
    "source_tier": "reputable",
    "confidence_status": "partial",
    "error": "",
    "name": "Bvlgari Octo Roma Worldtimer 103481",
    "collection": "Octo Roma",
    "mechanism": "Механический",
    "caliber": "BVL257",
    "diameter": "41 мм",
    "water_resistance": "100 м"
  },
  {
    "brand": "Alpina",
    "articul": "AL-525LBG4V6",
    "source_url": "https://azfinetime.com/products/alpina-al-525lbg4v6-seastrong-diver-300-automatic-black-dial",
    "source_tier": "unknown",
    "confidence_status": "partial",
    "error": "",
    "name": "Alpina Seastrong Diver 300 AL-525LBG4V6",
    "collection": "Seastrong Diver 300",
    "mechanism": "Механический",
    "caliber": "AL-525",
    "diameter": "44 мм",
    "water_resistance": "300 м"
  },
  {
    "brand": "Bomberg",
    "articul": "NS44CHPBA",
    "source_url": "https://www.timepiece.com/bomberg-bb-68-chronograph-quartz-black-dial-mens-watch-ns44chpba-200-9.html",
    "source_tier": "unknown",
    "confidence_status": "partial",
    "error": "",
    "name": "Bomberg BB-68 NS44CHPBA.200.9",
    "collection": "BB-68",
    "mechanism": "Кварцевый",
    "caliber": "Ronda 3520",
    "diameter": "44 мм",
    "water_resistance": "50 м"
  },
  {
    "brand": "Breitling",
    "articul": "A17367D71B1S1",
    "source_url": "https://www.breitling.com/ch-en/watches/superocean/superocean-automatic-44/A17367D71B1S1/",
    "source_tier": "official",
    "confidence_status": "partial",
    "error": "",
    "name": "Breitling Superocean Automatic 44 A17367D71B1S1",
    "collection": "Superocean",
    "mechanism": "Механический",
    "caliber": "не найдено",
    "diameter": "44.00 мм",
    "water_resistance": "1000.00 м"
  }
]